.gitattributes
.gitignore
LICENSE
MANIFEST.in
Makefile
README.md
README.rst
setup.cfg
setup.py
sandbox/cascade_trajectory.png
sandbox/example.py
sandbox/test_weighted_directed.py
thresholdmodel/__init__.py
thresholdmodel/metadata.py
thresholdmodel/model.py
thresholdmodel.egg-info/PKG-INFO
thresholdmodel.egg-info/SOURCES.txt
thresholdmodel.egg-info/dependency_links.txt
thresholdmodel.egg-info/not-zip-safe
thresholdmodel.egg-info/requires.txt
thresholdmodel.egg-info/top_level.txt