Metadata-Version: 1.1
Name: thresholdmodel
Version: 0.0.3
Summary: Simulate a continuous-time threshold model on static networks.
Home-page: https://github.com/benmaier/thresholdmodel
Author: Benjamin F. Maier
Author-email: bfmaier@physik.hu-berlin.de
License: MIT
Platform: UNKNOWN
Classifier: Programming Language :: Python :: 3
